pidevguru/__init__.py
pidevguru/piwebapi/__init__.py
pidevguru/piwebapi/api_client.py
pidevguru/piwebapi/pi_web_api_client.py
pidevguru/piwebapi/rest.py
pidevguru/piwebapi/controllers/__init__.py
pidevguru/piwebapi/controllers/analysis_category_controller_client.py
pidevguru/piwebapi/controllers/analysis_controller_client.py
pidevguru/piwebapi/controllers/analysis_rule_controller_client.py
pidevguru/piwebapi/controllers/analysis_rule_plug_in_controller_client.py
pidevguru/piwebapi/controllers/analysis_template_controller_client.py
pidevguru/piwebapi/controllers/asset_database_controller_client.py
pidevguru/piwebapi/controllers/asset_server_controller_client.py
pidevguru/piwebapi/controllers/attribute_category_controller_client.py
pidevguru/piwebapi/controllers/attribute_controller_client.py
pidevguru/piwebapi/controllers/attribute_template_controller_client.py
pidevguru/piwebapi/controllers/attribute_trait_controller_client.py
pidevguru/piwebapi/controllers/batch_controller_client.py
pidevguru/piwebapi/controllers/calculation_controller_client.py
pidevguru/piwebapi/controllers/channel_controller_client.py
pidevguru/piwebapi/controllers/configuration_controller_client.py
pidevguru/piwebapi/controllers/data_server_controller_client.py
pidevguru/piwebapi/controllers/element_category_controller_client.py
pidevguru/piwebapi/controllers/element_controller_client.py
pidevguru/piwebapi/controllers/element_template_controller_client.py
pidevguru/piwebapi/controllers/enumeration_set_controller_client.py
pidevguru/piwebapi/controllers/enumeration_value_controller_client.py
pidevguru/piwebapi/controllers/event_frame_controller_client.py
pidevguru/piwebapi/controllers/home_controller_client.py
pidevguru/piwebapi/controllers/notification_contact_template_controller_client.py
pidevguru/piwebapi/controllers/notification_plug_in_controller_client.py
pidevguru/piwebapi/controllers/notification_rule_controller_client.py
pidevguru_piwebapi-1.0.3.dist-info/LICENSE.md
pidevguru_piwebapi-1.0.3.dist-info/METADATA
pidevguru_piwebapi-1.0.3.dist-info/WHEEL
pidevguru_piwebapi-1.0.3.dist-info/top_level.txt
pidevguru_piwebapi-1.0.3.dist-info/RECORD
